{"digest":"a506b18b06c43cd4ce1c3ca53b92620a341fd15e","css":".project-manager-list-group {\n  color: #999999;\n  text-shadow: none;\n  padding: 1px 2px;\n  margin-left: 10px;\n  background: rgba(0, 0, 0, 0.1);\n  border-radius: 1px;\n}\n.selected .project-manager-list-group {\n  color: #444444;\n}\n.project-manager-devmode {\n  float: right;\n}\n.project-manager-devmode:before {\n  content: \"\\f065\";\n  color: #cc0000;\n  font-family: 'Octicons Regular';\n  font-weight: normal;\n  font-style: normal;\n  text-shadow: none;\n  font-size: 14px;\n  line-height: 1;\n  display: inline-block;\n}\n","imports":[{"path":"static/variables/ui-variables.less","digest":"db5eb421fee2d1e5cbcd22ab539614069fb815c8"},{"path":"static/variables/syntax-variables.less","digest":"dbb8bc25cbfa6ac53763293d81b25b8d718230f9"},{"path":"node_modules/atom-light-ui/stylesheets/ui-variables.less","digest":"52b1d1f989f08c3e99d7d022921fdd3d29f01a97"}],"version":1}